jaxlib/__init__.py
jaxlib/cpu_feature_guard.so
jaxlib/ducc_fft.py
jaxlib/gpu_linalg.py
jaxlib/gpu_prng.py
jaxlib/gpu_rnn.py
jaxlib/gpu_solver.py
jaxlib/gpu_sparse.py
jaxlib/hlo_helpers.py
jaxlib/lapack.py
jaxlib/py.typed
jaxlib/version.py
jaxlib/xla_client.py
jaxlib/xla_extension.so
jaxlib/cpu/_ducc_fft.so
jaxlib/cpu/_lapack.so
jaxlib/mlir/ir.py
jaxlib/mlir/passmanager.py
jaxlib/mlir/_mlir_libs/__init__.py
jaxlib/mlir/_mlir_libs/_chlo.so
jaxlib/mlir/_mlir_libs/_mlir.so
jaxlib/mlir/_mlir_libs/_mlirDialectsSparseTensor.so
jaxlib/mlir/_mlir_libs/_mlirHlo.so
jaxlib/mlir/_mlir_libs/_mlirSparseTensorPasses.so
jaxlib/mlir/_mlir_libs/_site_initialize_0.so
jaxlib/mlir/_mlir_libs/_stablehlo.so
jaxlib/mlir/_mlir_libs/libjaxlib_mlir_capi.so
jaxlib/mlir/dialects/_builtin_ops_ext.py
jaxlib/mlir/dialects/_builtin_ops_gen.py
jaxlib/mlir/dialects/_chlo_ops_gen.py
jaxlib/mlir/dialects/_func_ops_ext.py
jaxlib/mlir/dialects/_func_ops_gen.py
jaxlib/mlir/dialects/_mhlo_ops_gen.py
jaxlib/mlir/dialects/_ml_program_ops_ext.py
jaxlib/mlir/dialects/_ml_program_ops_gen.py
jaxlib/mlir/dialects/_ods_common.py
jaxlib/mlir/dialects/_sparse_tensor_ops_gen.py
jaxlib/mlir/dialects/_stablehlo_ops_gen.py
jaxlib/mlir/dialects/builtin.py
jaxlib/mlir/dialects/chlo.py
jaxlib/mlir/dialects/func.py
jaxlib/mlir/dialects/mhlo.py
jaxlib/mlir/dialects/ml_program.py
jaxlib/mlir/dialects/sparse_tensor.py
jaxlib/mlir/dialects/stablehlo.py
jaxlib/rocm/_blas.so
jaxlib/rocm/_linalg.so
jaxlib/rocm/_prng.so
jaxlib/rocm/_solver.so
jaxlib/rocm/_sparse.so
jaxlib/xla_extension/__init__.pyi
jaxlib/xla_extension/jax_jit.pyi
jaxlib/xla_extension/ops.pyi
jaxlib/xla_extension/outfeed_receiver.pyi
jaxlib/xla_extension/pmap_lib.pyi
jaxlib/xla_extension/profiler.pyi
jaxlib/xla_extension/pytree.pyi
jaxlib/xla_extension/transfer_guard_lib.pyi
jaxlib_rocm-0.4.6.5401.dist-info/LICENSE.txt
jaxlib_rocm-0.4.6.5401.dist-info/METADATA
jaxlib_rocm-0.4.6.5401.dist-info/WHEEL
jaxlib_rocm-0.4.6.5401.dist-info/top_level.txt
jaxlib_rocm-0.4.6.5401.dist-info/RECORD
