Metadata-Version: 2.1
Name: jaxlib-rocm
Version: 0.4.6.5401
Summary: XLA library for JAX
Home-page: https://github.com/google/jax
Author: JAX team
Author-email: jax-dev@google.com
License: Apache-2.0
Classifier: Programming Language :: Python :: 3.8
Classifier: Programming Language :: Python :: 3.9
Classifier: Programming Language :: Python :: 3.10
Classifier: Programming Language :: Python :: 3.11
Requires-Python: >=3.8
License-File: LICENSE.txt
Requires-Dist: scipy (>=1.5)
Requires-Dist: numpy (>=1.20)
